RanCE/__init__.py
RanCE/random_code_gen.py
RanCE/template.py
RanCE-0.0.2.dist-info/METADATA
RanCE-0.0.2.dist-info/WHEEL
RanCE-0.0.2.dist-info/top_level.txt
RanCE-0.0.2.dist-info/RECORD
