Metadata-Version: 2.1
Name: RanCE
Version: 0.0.2
Summary: Random Code Emitter
Author: Featureprenuer
License: UNKNOWN
Platform: UNKNOWN
Classifier: Programming Language :: Python :: 3
Classifier: License :: OSI Approved :: MIT License
Classifier: Operating System :: OS Independent
Requires-Python: >=3.6
Requires-Dist: beautifulsoup4
Requires-Dist: twine
Requires-Dist: setuptools
Requires-Dist: wheel
